upgradeChat/__init__.py
upgradeChat/api.py
upgradeChat/utils.py
upgradeChat/models/__init__.py
upgradeChat/models/order.py
upgradeChat/models/orders.py
upgradeChat/models/product.py
upgradeChat/models/products.py
upgradeChat/models/user.py
upgradeChat/models/users.py
upgradeChat/models/webhook.py
upgradeChat/models/webhook_event.py
upgradeChat/models/webhook_events.py
upgradeChat/models/webhooks.py
upgradeChat-0.1.2.dist-info/LICENSE
upgradeChat-0.1.2.dist-info/METADATA
upgradeChat-0.1.2.dist-info/WHEEL
upgradeChat-0.1.2.dist-info/top_level.txt
upgradeChat-0.1.2.dist-info/RECORD
