Metadata-Version: 2.1
Name: upgradeChat
Version: 0.1.2
Summary: A complete Python client for Upgrade.Chat's API
Home-page: https://github.com/nwithan8/upgradeChat
Author: Nate Harris
Author-email: n8gr8gbln@gmail.com
License: GNU General Public License v3 (GPLv3)
Download-URL: https://github.com/nwithan8/upgradeChat/archive/0.1.2.tar.gz
Keywords: Discord,chat,bot,Upgrade.Chat,donations,subscriptions,rewards,management,API,client
Platform: UNKNOWN
Classifier: License :: OSI Approved :: GNU General Public License v3 (GPLv3)
Classifier: Development Status :: 4 - Beta
Classifier: Intended Audience :: Developers
Classifier: Topic :: Software Development :: Build Tools
Classifier: Programming Language :: Python :: 3
Classifier: Programming Language :: Python :: 3.7
Classifier: Programming Language :: Python :: 3.8
Classifier: Programming Language :: Python :: 3.9
Classifier: Topic :: Multimedia :: Video
Classifier: Topic :: Multimedia
Classifier: Topic :: Internet :: WWW/HTTP
Classifier: Operating System :: OS Independent
Requires-Python: >=3.7
Requires-Dist: objectrest (>=0.2.0)
Requires-Dist: pydantic (>=1.8.1)
Requires-Dist: requests (>=2.25.1)
